LICENSE.txt
README.rst
setup.py
xrenner/__init__.py
xrenner/run_xrenner.py
xrenner/xrenner.py
xrenner.egg-info/PKG-INFO
xrenner.egg-info/SOURCES.txt
xrenner.egg-info/dependency_links.txt
xrenner.egg-info/requires.txt
xrenner.egg-info/top_level.txt
xrenner/licenses/LICENSE_DBpedia.txt
xrenner/licenses/LICENSE_EWT.txt
xrenner/licenses/LICENSE_GUM.txt
xrenner/licenses/LICENSE_GeoNames.txt
xrenner/licenses/LICENSE_GoogleNewsVectors.txt
xrenner/licenses/LICENSE_OntoNotes.txt
xrenner/licenses/LICENSE_PPDB.txt
xrenner/licenses/LICENSE_PTB.txt
xrenner/licenses/LICENSE_Scriptorium.txt
xrenner/licenses/LICENSE_UKWAC.txt
xrenner/licenses/LICENSE_WordNet.txt
xrenner/models/cop.xrm
xrenner/models/cop_orig.xrm_old
xrenner/models/eng.xrm
xrenner/models/eng_old.xrm_old
xrenner/models/models_go_here
xrenner/models/_sequence_taggers/sequence_labelers_here.md
xrenner/modules/__init__.py
xrenner/modules/depedit.py
xrenner/modules/get_models.py
xrenner/modules/timing.py
xrenner/modules/xrenner_classes.py
xrenner/modules/xrenner_classify.py
xrenner/modules/xrenner_compatible.py
xrenner/modules/xrenner_coref.py
xrenner/modules/xrenner_lex.py
xrenner/modules/xrenner_marker.py
xrenner/modules/xrenner_ontoreader.py
xrenner/modules/xrenner_out.py
xrenner/modules/xrenner_parse.py
xrenner/modules/xrenner_postprocess.py
xrenner/modules/xrenner_preprocess.py
xrenner/modules/xrenner_propagate.py
xrenner/modules/xrenner_rule.py
xrenner/modules/xrenner_sequence.py
xrenner/modules/xrenner_test.py
xrenner/modules/xrenner_xrenner.py
xrenner/test/tests.dat