Metadata-Version: 2.1
Name: xrenner
Version: 2.2.1.1
Summary: A configurable, language independent coreferencer and (non) named entity recognizer
Home-page: https://github.com/amir-zeldes/xrenner
Download-URL: https://github.com/amir-zeldes/xrenner/releases/tag/v2.2.1.1
Author: Amir Zeldes
Author-email: amir.zeldes@georgetown.edu
License: Apache License, Version 2.0
Keywords: NLP,coreference,NER,named entity
Classifier: Programming Language :: Python
Classifier: Programming Language :: Python :: 2
Classifier: Programming Language :: Python :: 3
Classifier: License :: OSI Approved :: Apache Software License
Classifier: Operating System :: OS Independent
License-File: LICENSE.txt
